<Root>
    <File Name="object_oE6" Segment="6">
        <Array Name="object_oE6_Vtx_000000" Count="174" Offset="0x0">
            <Vtx/>
        </Array>
        <DList Name="object_oE6_DL_000AE0" Offset="0xAE0"/>
        <Texture Name="object_oE6_TLUT_000FD0" Format="rgba16" Width="16" Height="16" Offset="0xFD0"/>
        <Texture Name="object_oE6_Tex_0011D0" Format="ci8" Width="32" Height="32" Offset="0x11D0" TlutOffset="0xFD0"/>
        <Texture Name="object_oE6_Tex_0015D0" Format="ci8" Width="32" Height="32" Offset="0x15D0" TlutOffset="0xFD0"/>
        <Texture Name="object_oE6_Tex_0019D0" Format="ci8" Width="32" Height="32" Offset="0x19D0" TlutOffset="0xFD0"/>
        <Texture Name="object_oE6_TLUT_001DD0" Format="rgba16" Width="16" Height="16" Offset="0x1DD0"/>
        <Texture Name="object_oE6_Tex_001FD0" Format="ci8" Width="8" Height="8" Offset="0x1FD0" TlutOffset="0x1DD0"/>
        <Texture Name="object_oE6_Tex_002010" Format="ci8" Width="16" Height="16" Offset="0x2010" TlutOffset="0x1DD0"/>
        <Texture Name="object_oE6_Tex_002110" Format="rgba16" Width="8" Height="16" Offset="0x2110"/>
        <Texture Name="object_oE6_Tex_002210" Format="rgba16" Width="32" Height="32" Offset="0x2210"/>
        <Texture Name="object_oE6_Tex_002A10" Format="rgba16" Width="32" Height="16" Offset="0x2A10"/>
        <Texture Name="object_oE6_Tex_002E10" Format="i4" Width="16" Height="8" Offset="0x2E10"/>
    </File>
</Root>
