<Root>
    <ExternalFile OutPath="assets/objects/gameplay_keep"/>
    <File Name="object_gi_ocarina_0" Segment="6">
        <Texture Name="object_gi_ocarina_0_000000_Tex" Format="i8" Width="16" Height="16" Offset="0x0"/>
        <Array Name="gGiOcarinaFairyVtx" Count="105" Offset="0x100">
            <Vtx/>
        </Array>
        <Array Name="gGiOcarinaFairyHolesVtx" Count="21" Offset="0x790">
            <Vtx/>
        </Array>
        <DList Name="gGiOcarinaFairyDL" Offset="0x08E0"/>
        <DList Name="gGiOcarinaFairyHolesDL" Offset="0x0B58"/>
    </File>
</Root>
